MANIFEST.in
setup.cfg
setup.py
data/test.txt
ext/__init__.py
ext/contextmanager/__init__.py
ext/jupyter/__init__.py
ext/pandas/__init__.py
ext/pandas/dgDataFrame.py
gis/__init__.py
gis/coord_transform.py
gui/__init__.py
snippets/database.ipynb
tonnyma_utils.egg-info/PKG-INFO
tonnyma_utils.egg-info/SOURCES.txt
tonnyma_utils.egg-info/dependency_links.txt
tonnyma_utils.egg-info/requires.txt
tonnyma_utils.egg-info/top_level.txt
tools/gis_tool/MyWidgets.py
tools/gis_tool/main.py
tools/gis_tool/icons/extent.png
tools/gis_tool/icons/icon.png
tools/gis_tool/icons/pan.png
tools/gis_tool/icons/plot.png
tools/gis_tool/icons/tracks.png
tools/gis_tool/icons/zoomin.png
tools/gis_tool/icons/zoomout.png
tools/gis_tool/temp/a.aux
tools/gis_tool/temp/a.cpp
tools/gis_tool/temp/a.fdb_latexmk
tools/gis_tool/temp/a.fls
tools/gis_tool/temp/a.log
tools/gis_tool/temp/a.pdf
tools/gis_tool/temp/a.py
tools/gis_tool/temp/a.tex
tools/gis_tool/temp/_minted-a/default.pygstyle
tools/gis_tool/tracks/random.gpx
tools/gis_tool/tracks/random2.gpx
tools/gis_tool/tracks/random3.gpx
tools/pipe/plot.py
tools/pipe/readme.md
tools/pipe/serve.py
tools/watermark/watermark.pdf
tools/watermark/watermark.py
tools/workflow/workflow.json
tools/workflow/workflow.py
transportation/__init__.py
transportation/base/__init__.py
transportation/base/mapmatching.py