Metadata-Version: 2.1
Name: tonnyma-utils
Version: 0.0.1
Summary: A project created for convenience
Home-page: UNKNOWN
Author: Jiangshan Ma
Author-email: tonny.achilles@gmail.com
License: UNKNOWN
Project-URL: Funding, https://donate.pypi.org
Project-URL: Bug Reports, https://github.com/pypa/sampleproject/issues
Project-URL: Say Thanks!, http://saythanks.io/to/example
Project-URL: Source, https://github.com/pypa/sampleproject/
Keywords: sample setuptools development
Platform: UNKNOWN
Classifier: Development Status :: 3 - Alpha
Classifier: Intended Audience :: Developers
Classifier: Topic :: Software Development :: Build Tools
Classifier: License :: OSI Approved :: MIT License
Classifier: Programming Language :: Python :: 2
Classifier: Programming Language :: Python :: 2.7
Classifier: Programming Language :: Python :: 3
Classifier: Programming Language :: Python :: 3.4
Classifier: Programming Language :: Python :: 3.5
Classifier: Programming Language :: Python :: 3.6
Provides-Extra: test
Provides-Extra: dev
